{
  "subject_code": "WME01",
  "paper": {
    "year": 2015,
    "season": "Jun",
    "paper_number": "P1"
  },
  "questions": [
    {
      "qnum": 1,
      "qp_pages": [
        0,
        1,
        2,
        3,
        4,
        5,
        6,
        7,
        8,
        9
      ],
      "ms_pages": [
        15
      ],
      "marks_ms": 216,
      "marks_meta": {
        "mode": "summed"
      }
    },
    {
      "qnum": 2,
      "qp_pages": [
        0,
        1,
        2,
        3,
        4,
        5,
        6,
        7,
        8,
        9
      ],
      "ms_pages": [],
      "marks_ms": null,
      "marks_meta": {
        "mode": "no_pages"
      }
    },
    {
      "qnum": 3,
      "qp_pages": [
        0,
        1,
        2,
        3,
        4,
        5,
        6,
        7,
        8
      ],
      "ms_pages": [
        15
      ],
      "marks_ms": 216,
      "marks_meta": {
        "mode": "summed"
      }
    },
    {
      "qnum": 4,
      "qp_pages": [
        9
      ],
      "ms_pages": [],
      "marks_ms": null,
      "marks_meta": {
        "mode": "no_pages"
      }
    },
    {
      "qnum": 5,
      "qp_pages": [
        0,
        1,
        2,
        3,
        4,
        5,
        6,
        7,
        8,
        9
      ],
      "ms_pages": [],
      "marks_ms": null,
      "marks_meta": {
        "mode": "no_pages"
      }
    },
    {
      "qnum": 6,
      "qp_pages": [
        0,
        1,
        2,
        3,
        4,
        5,
        6,
        7,
        8,
        9
      ],
      "ms_pages": [
        14
      ],
      "marks_ms": 16,
      "marks_meta": {
        "mode": "summed"
      }
    },
    {
      "qnum": 7,
      "qp_pages": [
        0,
        1,
        2,
        3,
        4,
        5,
        6,
        7,
        8,
        9
      ],
      "ms_pages": [
        15
      ],
      "marks_ms": 216,
      "marks_meta": {
        "mode": "summed"
      }
    },
    {
      "qnum": 8,
      "qp_pages": [
        0,
        1,
        2,
        3,
        4,
        5,
        6,
        7,
        8,
        9
      ],
      "ms_pages": [
        17
      ],
      "marks_ms": 43,
      "marks_meta": {
        "mode": "summed"
      }
    }
  ],
  "metrics": {
    "question_count": 8,
    "ms_linking_pct": 62.5,
    "qp_pages": 10,
    "ms_pages": 20
  }
}